packing3d/__init__.py
packing3d/cartesian.py
packing3d/cylindrical.py
packing3d/geometry.py
packing3d/io.py
packing3d/mesh.py
packing3d/utils.py
packing3d/examples/examples.py
packing3d/examples/post/centered_simple_cubic_spheres_68921.vtk
packing3d/examples/post/particles_1700000.vtk
packing3d/examples/post/particles_cooleffect.vtk
packing3d-0.1.7.dist-info/LICENSE
packing3d-0.1.7.dist-info/METADATA
packing3d-0.1.7.dist-info/WHEEL
packing3d-0.1.7.dist-info/top_level.txt
packing3d-0.1.7.dist-info/RECORD
