Metadata-Version: 2.1
Name: packing3d
Version: 0.1.7
Summary: A package for calculating packing density of particles in Cartesian and cylindrical coordinate systems.
Author-email: Freddie Barter <fjbarter@outlook.com>
License:                     GNU GENERAL PUBLIC LICENSE
Keywords: packing density,cartesian,cylindrical,geometry,particles,segregation
Classifier: Development Status :: 4 - Beta
Classifier: Intended Audience :: Science/Research
Classifier: Programming Language :: Python :: 3
Classifier: License :: OSI Approved :: GNU General Public License v3 (GPLv3)
Classifier: Topic :: Scientific/Engineering :: Physics
Requires-Python: >=3.8
License-File: LICENSE
Requires-Dist: numpy>=1.21
Requires-Dist: pyvista>=0.34
